[
    {
        "ObjectSlug": "Sword",
        "ItemName": "Sword",
        "Description": "A long, sharp blade.",
        "ItemType": "Weapon",
        "ActionName": "Equip",
        "ItemModifier": 0,
        "Stats": [
            {
                "StatType": "Attack",
                "BaseValue": 25,
                "StatName": "Attack"
            },
            {
                "StatType": "Defense",
                "BaseValue": 4,
                "StatName": "Defense"
            },
            {
                "StatType": "AttackSpeed",
                "BaseValue": 4,
                "StatName": "Attack Speed"
            }
        ]
    },
    {
        "ObjectSlug": "Staff",
        "ItemName": "Staff",
        "Description": "A magical staff that casts fireballs.",
        "ItemType": "Weapon",
        "ActionName": "Equip",
        "ItemModifier": 0,
        "Stats": [
            {
                "StatType": "Attack",
                "BaseValue": 18,
                "StatName": "Attack"
            },
            {
                "StatType": "Defense",
                "BaseValue": 2,
                "StatName": "Defense"
            },
            {
                "StatType": "AttackSpeed",
                "BaseValue": 6,
                "StatName": "Attack Speed"
            }
        ]
    },
    {
        "ObjectSlug": "Potion_Log",
        "ItemName": "Log Potion",
        "Description": "A potion that heals 30 HP.",
        "ItemType": "Consumable",
        "ActionName": "Drink",
        "ItemModifier": 0
    }
]